PAMMySQLTools-0.2.1.dist-info/DESCRIPTION.rst
PAMMySQLTools-0.2.1.dist-info/METADATA
PAMMySQLTools-0.2.1.dist-info/RECORD
PAMMySQLTools-0.2.1.dist-info/WHEEL
PAMMySQLTools-0.2.1.dist-info/entry_points.txt
PAMMySQLTools-0.2.1.dist-info/metadata.json
PAMMySQLTools-0.2.1.dist-info/top_level.txt
pammysqltools/__init__.py
pammysqltools/helpers.py
pammysqltools/manager.py
pammysqltools/scripts.py
pammysqltools/validators.py
pammysqltools/locales/de_DE/LC_MESSAGES/messages.mo
pammysqltools/locales/en/LC_MESSAGES/messages.mo
tests/__init__.py
tests/test_helpers.py
tests/test_manager.py
