Metadata-Version: 2.0
Name: PAMMySQLTools
Version: 0.2.1
Summary: A set of tools to manage users from pam_mysql
Home-page: https://github.com/cperrin88/PAMMySQLTools
Author: Christopher Perrin
Author-email: perrin@uni-trier.de
License: MIT
Platform: UNKNOWN
Classifier: License :: OSI Approved :: MIT License
Classifier: Environment :: Console
Requires-Dist: click
Requires-Dist: configparser (>=3.5.0b2)
Requires-Dist: future
Requires-Dist: pymysql
Requires-Dist: six
